mitemp_cgg1/__init__.py
mitemp_cgg1/mitemp_cgg1_poller.py
mitemp_cgg1-0.0.1.dist-info/LICENSE
mitemp_cgg1-0.0.1.dist-info/METADATA
mitemp_cgg1-0.0.1.dist-info/WHEEL
mitemp_cgg1-0.0.1.dist-info/top_level.txt
mitemp_cgg1-0.0.1.dist-info/RECORD
