Metadata-Version: 2.1
Name: mitemp-cgg1
Version: 0.0.1
Summary: Library to read data from Xiaomi Clear Grass Thermometer Hygrometer sensor with E-Ink
Home-page: https://github.com/KalininAndreyVictorovich/mitemp_cgg1
Author: Andrey
Author-email: kalininandreyvictorovich@gmail.com
License: MIT
Keywords: temperature humidity sensor bluetooth low-energy ble Xiaomi ClearGrass
Platform: UNKNOWN
Classifier: Development Status :: 3 - Alpha
Classifier: Intended Audience :: Developers
Classifier: Topic :: System :: Hardware :: Hardware Drivers
Classifier: License :: OSI Approved :: MIT License
Classifier: Programming Language :: Python :: 3
Classifier: Programming Language :: Python :: 3.7
Requires-Dist: bluepy (==1.3.0)
